anage.py
anage-0.0.2.dist-info/LICENSE
anage-0.0.2.dist-info/WHEEL
anage-0.0.2.dist-info/METADATA
anage-0.0.2.dist-info/RECORD
