Metadata-Version: 2.1
Name: anage
Version: 0.0.2
Summary: python -manage packages
Home-page: https://sr.ht/~cnx/anage
License: GPLv3+
Keywords: package manager
Author: Nguyễn Gia Phong
Author-email: mcsinyx@disroot.org
Requires-Python: >=3.6
Classifier: Development Status :: 2 - Pre-Alpha
Classifier: Environment :: Console
Classifier: Intended Audience :: End Users/Desktop
Classifier: License :: OSI Approved :: GNU General Public License v3 or later (GPLv3+)
Classifier: Natural Language :: English
Classifier: Operating System :: OS Independent
Classifier: Programming Language :: Python :: 3 :: Only
Classifier: Programming Language :: Python :: 3.6
Classifier: Programming Language :: Python :: 3.7
Classifier: Programming Language :: Python :: 3.8
Classifier: Programming Language :: Python :: 3.9
Classifier: Topic :: Utilities
Classifier: Typing :: Typed
Requires-Dist: appdirs
Requires-Dist: click
Requires-Dist: importlib_metadata; python_version < "3.8"
Requires-Dist: pip
Requires-Dist: packaging
